<?xml version = '1.0' encoding = 'UTF-8'?>
<Relation class="oracle.dbtools.crest.model.design.logical.Relation" name="Relation_72" directorySegmentName="seg_0" id="C0B43D60-AC3B-4F33-170B-7D604E1D8BE6">
<createdBy>Personal</createdBy>
<createdTime>2020-11-23 20:44:11 UTC</createdTime>
<ownerDesignName>bases1</ownerDesignName>
<engineerTo>
<item key="8FFA3864-83E6-6C44-D83D-F300AD2C333A" value="true"/>
</engineerTo>
<sourcePk>D583D49A-1ACD-2A52-DCC0-9C1988DAB7B4</sourcePk>
<identifying>true</identifying>
<optionalSource>true</optionalSource>
<optionalTarget>false</optionalTarget>
<sourceCardinality>1</sourceCardinality>
<sourceEntity>E384FAE6-D113-FBE7-6197-D365D8092558</sourceEntity>
<targetCardinalityString>*</targetCardinalityString>
<targetEntity>F25DADC6-4D8A-137A-2C4A-7E98BAE350AF</targetEntity>
<transferable>true</transferable>
<deleteRule>NO ACTION</deleteRule>
</Relation>
